aiogarmin/__init__.py
aiogarmin/auth.py
aiogarmin/client.py
aiogarmin/const.py
aiogarmin/exceptions.py
aiogarmin/fit.py
aiogarmin/models.py
aiogarmin/py.typed
aiogarmin-0.1.4.dist-info/licenses/LICENSE
aiogarmin-0.1.4.dist-info/METADATA
aiogarmin-0.1.4.dist-info/WHEEL
aiogarmin-0.1.4.dist-info/top_level.txt
aiogarmin-0.1.4.dist-info/RECORD
