Metadata-Version: 2.4
Name: aiogarmin
Version: 0.1.4
Summary: Async Python client for Garmin Connect API
Author-email: Ron Klinkien <ron@cyberjunky.nl>
License: MIT
Project-URL: Homepage, https://github.com/cyberjunky/aiogarmin
Project-URL: Repository, https://github.com/cyberjunky/aiogarmin
Project-URL: Documentation, https://github.com/cyberjunky/aiogarmin#readme
Project-URL: Issues, https://github.com/cyberjunky/aiogarmin/issues
Project-URL: Changelog, https://github.com/cyberjunky/aiogarmin/releases
Keywords: garmin,garmin-connect,fitness,async,api,health
Classifier: Development Status :: 4 - Beta
Classifier: Intended Audience :: Developers
Classifier: License :: OSI Approved :: MIT License
Classifier: Operating System :: OS Independent
Classifier: Programming Language :: Python :: 3
Classifier: Programming Language :: Python :: 3.11
Classifier: Programming Language :: Python :: 3.12
Classifier: Programming Language :: Python :: 3.13
Classifier: Framework :: AsyncIO
Classifier: Topic :: Software Development :: Libraries :: Python Modules
Classifier: Topic :: Internet :: WWW/HTTP
Classifier: Typing :: Typed
Requires-Python: >=3.11
License-File: LICENSE
Requires-Dist: aiohttp>=3.8.0
Requires-Dist: pydantic>=2.0.0
Requires-Dist: oauthlib>=3.2.0
Provides-Extra: dev
Requires-Dist: pytest>=7.0.0; extra == "dev"
Requires-Dist: pytest-asyncio>=0.21.0; extra == "dev"
Requires-Dist: pytest-aiohttp>=1.0.0; extra == "dev"
Requires-Dist: pytest-cov>=4.0.0; extra == "dev"
Requires-Dist: aioresponses>=0.7.0; extra == "dev"
Requires-Dist: ruff>=0.1.0; extra == "dev"
Requires-Dist: mypy>=1.0.0; extra == "dev"
Requires-Dist: build>=1.0.0; extra == "dev"
Requires-Dist: twine>=4.0.0; extra == "dev"
Dynamic: license-file
